{"2019": {"47": {"commits": 5, "email": {"fromMe": 133, "toMe": 439}, "location": {"Amsterdam, Netherlands": [[{"label": "display", "lat": 52.37206542660903, "lng": 4.889217007892203}], [{"label": "display", "lat": 52.371641, "lng": 4.88955}], [{"label": "display", "lat": 52.37206542660903, "lng": 4.889217007892203}], [{"label": "display", "lat": 52.37206542660903, "lng": 4.889217007892203}]], "Schiphol, Netherlands": [[{"label": "display", "lat": 52.3085704596075, "lng": 4.762122631072998}], [{"label": "display", "lat": 52.3085704596075, "lng": 4.762122631072998}]], "Soho, United Kingdom": [[{"label": "display", "lat": 51.513344465324636, "lng": -0.13060197600653342}]], "London, United Kingdom": [[{"label": "display", "lat": 51.52378114, "lng": -0.07593268}], [{"label": "display", "lat": 51.50171449750539, "lng": -0.023607648764287188}]]}}}}