{"2019": {"20": {"location": {"Eindhoven, Netherlands": [[{"lat": 51.441064187970234, "label": "display", "lng": 5.480123160269741}]], "The Hague, Netherlands": [[{"lat": 52.07977022603392, "label": "display", "lng": 4.306521829547891}], [{"lat": 52.079191978807756, "label": "display", "lng": 4.308131462089512}]], "Amsterdam, Netherlands": [[{"lat": 52.366832338021034, "label": "display", "lng": 4.8688868799837035}], [{"lat": 52.371641, "label": "display", "lng": 4.88955}], [{"lat": 52.364956864830525, "label": "display", "lng": 4.9361016863983185}], [{"lat": 52.371641, "label": "display", "lng": 4.88955}], [{"lat": 52.371641, "label": "display", "lng": 4.88955}]]}, "commits": 20, "email": {"fromMe": 119, "toMe": 398}}}}