{"2019": {"21": {"commits": 22, "meetings": {"meetings": 46, "people": 45}, "email": {"toMe": 291, "fromMe": 45}, "location": {"Hay-on-wye, United Kingdom": [[{"lat": 52.074733865669444, "lng": -3.1248760087455927, "label": "display"}], [{"lat": 52.074719, "lng": -3.124838, "label": "display"}], [{"lat": 52.074719, "lng": -3.124838, "label": "display"}]], "Schiphol, Netherlands": [[{"lat": 52.3085704596075, "lng": 4.762122631072998, "label": "display"}]], "Worcester, United Kingdom": [[{"lat": 52.175997892358666, "lng": -2.2876831188375113, "label": "display"}]]}}}}